gremux/__init__.py
gremux/cli.py
gremux/core.py
gremux/cmds/__init__.py
gremux/cmds/config.py
gremux/cmds/places.py
gremux/cmds/sessionizer.py
gremux/struct/__init__.py
gremux/struct/context.py
gremux/struct/grem.py
gremux/struct/logger.py
gremux/struct/parser.py
gremux-0.1.1.dist-info/licenses/LICENSE
gremux-0.1.1.dist-info/METADATA
gremux-0.1.1.dist-info/WHEEL
gremux-0.1.1.dist-info/entry_points.txt
gremux-0.1.1.dist-info/top_level.txt
gremux-0.1.1.dist-info/RECORD
