Metadata-Version: 2.4
Name: gremux
Version: 0.1.1
Summary: A declarative tmux session manager
Author-email: leogabac <leogabac@proton.me>
License: GPLv2
Project-URL: Homepage, https://github.com/leogabac/gremux
Project-URL: Repository, https://github.com/leogabac/gremux
Project-URL: Issues, https://github.com/leogabac/gremux/issues
Keywords: tmux,terminal,session-manager,cli,developer-tools
Classifier: Development Status :: 3 - Alpha
Classifier: Environment :: Console
Classifier: Intended Audience :: Developers
Classifier: License :: OSI Approved :: GNU General Public License v2 (GPLv2)
Classifier: Operating System :: POSIX :: Linux
Classifier: Programming Language :: Python :: 3
Classifier: Programming Language :: Python :: 3 :: Only
Classifier: Programming Language :: Python :: 3.9
Classifier: Programming Language :: Python :: 3.10
Classifier: Programming Language :: Python :: 3.11
Classifier: Programming Language :: Python :: 3.12
Classifier: Topic :: Software Development :: Build Tools
Classifier: Topic :: System :: Shells
Classifier: Topic :: Utilities
Requires-Python: >=3.9
License-File: LICENSE
Requires-Dist: libtmux>=0.39
Requires-Dist: pyyaml>=6.0
Dynamic: license-file
